lk_ml_package/__init__.py
lk_ml_package/api.py
lk_ml_package/cache.py
lk_ml_package/exceptions.py
lk_ml_package/model.py
lk_ml_package/server.py
lk_ml_package/utils.py
lk_ml_package/wsgi.py
ml_package/__init__.py
ml_package/api.py
ml_package/cache.py
ml_package/exceptions.py
ml_package/model.py
ml_package/server.py
ml_package/utils.py
ml_package/wsgi.py
lk_ml_package-1.0.0.dist-info/METADATA
lk_ml_package-1.0.0.dist-info/WHEEL
lk_ml_package-1.0.0.dist-info/entry_points.txt
lk_ml_package-1.0.0.dist-info/top_level.txt
lk_ml_package-1.0.0.dist-info/RECORD
