Metadata-Version: 2.1
Name: lk-ml-package
Version: 1.0.0
Summary: machine learning
Home-page: https://gitlab.enncloud.cn/ai_data_management/server/machine-learning.git
Author: fengjiansong
Author-email: fengjiansong@enn.cn
Classifier: Programming Language :: Python :: 3
Classifier: License :: OSI Approved :: MIT License
Classifier: Operating System :: OS Independent
Requires-Python: >=3.8
Requires-Dist: Flask ~=2.3
Requires-Dist: colorama ~=0.4
Requires-Dist: requests ~=2.31
Requires-Dist: label-studio-tools
